{
  "rounds": [
    {
      "success": ["start", "начать", "8 марта", "что происходит", "говори", "привет", "старт"],
      "hints": ["Меня зовут Джарвис! Давайте попробуем начать"]
    },
    {
      "output": [
          {
            "text": "Приветствую!",
            "timer": 0
          },
          {
            "text": "Меня зовут Джарвис.",
            "timer": 4000
          },
          {
            "text": "Я поздравляю прекрасных девушек жи жи эр сии с 8-м марта!",
            "timer": 4000
          },
          {
            "text": "Сегодня я помогу вам отыскать ништяки которые от вас спрятаны.",
            "timer": 8000
          },
          {
            "text": "Давайте попробуем пообщаться",
            "timer": 14000
          },
          {
            "text": "Какой цветок является символом весны?",
            "timer": 4000
          }
      ],
      "success": ["тюльпан"]
    },
    {
      "output": [
        {
          "text": "Да, это тюльпан",
          "timer": 0
        },
        {
          "text": "Да, это тюльпан",
          "timer": 0
        }
      ]
    }
  ]
}